README.md
setup.py
pfpi/__init__.py
pfpi/exceptions.py
pfpi/fields.py
pfpi/services.py
pfpi/utils.py
pfpi.egg-info/PKG-INFO
pfpi.egg-info/SOURCES.txt
pfpi.egg-info/dependency_links.txt
pfpi.egg-info/top_level.txt