Metadata-Version: 2.1
Name: pfpi
Version: 1.0.1
Summary: Interface to do payments through Paguelo Facil gateway
Home-page: https://github.com/franklintiel/pfig/wiki
Author: Franklin Sarmiento
Author-email: franklinitiel@gmail.com
License: MIT
Project-URL: Source, https://github.com/franklintiel/pfig
Project-URL: Documentation, https://github.com/franklintiel/pfig
Project-URL: Tracker, https://github.com/franklintiel/pfig/issues
Keywords: payments gateway paguelo-facil paguelo facil pfig
Platform: UNKNOWN
Classifier: Development Status :: 5 - Production/Stable
Classifier: License :: OSI Approved :: MIT License
Classifier: Programming Language :: Python :: 2.7
Classifier: Intended Audience :: Developers
Classifier: Natural Language :: English
Requires-Python: >=2.*
